sw/dbsync/__init__.py
sw/dbsync/dbapi.py
sw/dbsync/dbsync.py
sw/dbsync/py.typed
sw.dbsync-1.0.1.dist-info/LICENSE
sw.dbsync-1.0.1.dist-info/WHEEL
sw.dbsync-1.0.1.dist-info/METADATA
sw.dbsync-1.0.1.dist-info/RECORD
