Metadata-Version: 2.1
Name: sw.dbsync
Version: 1.0.1
Summary: Implementation of a database synchronization schema for PEP 249 compliant databases.
License: MIT
Keywords: database,synchronization,jsonschema
Author: Simon Wrede
Author-email: simwr872@student.liu.se
Requires-Python: >=3.9,<4.0
Classifier: Development Status :: 4 - Beta
Classifier: Intended Audience :: Developers
Classifier: License :: OSI Approved :: MIT License
Classifier: Natural Language :: English
Classifier: Operating System :: OS Independent
Classifier: Programming Language :: Python :: 3
Classifier: Programming Language :: Python :: 3.9
Classifier: Topic :: Database
Classifier: Topic :: Software Development :: Libraries :: Python Modules
Classifier: Typing :: Typed
